ocf_data_sampler/__init__.py
ocf_data_sampler/utils.py
ocf_data_sampler/config/__init__.py
ocf_data_sampler/config/load.py
ocf_data_sampler/config/model.py
ocf_data_sampler/config/save.py
ocf_data_sampler/gsp_location_data_legacy_format/uk_gsp_locations_20220314.csv
ocf_data_sampler/gsp_location_data_legacy_format/uk_gsp_locations_20250109.csv
ocf_data_sampler/load/__init__.py
ocf_data_sampler/load/generation.py
ocf_data_sampler/load/load_dataset.py
ocf_data_sampler/load/open_xarray_tensorstore.py
ocf_data_sampler/load/satellite.py
ocf_data_sampler/load/utils.py
ocf_data_sampler/load/nwp/__init__.py
ocf_data_sampler/load/nwp/nwp.py
ocf_data_sampler/load/nwp/providers/__init__.py
ocf_data_sampler/load/nwp/providers/cloudcasting.py
ocf_data_sampler/load/nwp/providers/ecmwf.py
ocf_data_sampler/load/nwp/providers/gdm.py
ocf_data_sampler/load/nwp/providers/gfs.py
ocf_data_sampler/load/nwp/providers/icon.py
ocf_data_sampler/load/nwp/providers/ukv.py
ocf_data_sampler/load/nwp/providers/utils.py
ocf_data_sampler/numpy_sample/__init__.py
ocf_data_sampler/numpy_sample/collate.py
ocf_data_sampler/numpy_sample/common_types.py
ocf_data_sampler/numpy_sample/datetime_features.py
ocf_data_sampler/numpy_sample/generation.py
ocf_data_sampler/numpy_sample/nwp.py
ocf_data_sampler/numpy_sample/satellite.py
ocf_data_sampler/numpy_sample/sun_position.py
ocf_data_sampler/select/__init__.py
ocf_data_sampler/select/diff_channels.py
ocf_data_sampler/select/dropout.py
ocf_data_sampler/select/fill_time_periods.py
ocf_data_sampler/select/find_contiguous_time_periods.py
ocf_data_sampler/select/geospatial.py
ocf_data_sampler/select/location.py
ocf_data_sampler/select/select_spatial_slice.py
ocf_data_sampler/select/select_time_slice.py
ocf_data_sampler/torch_datasets/pvnet_dataset.py
ocf_data_sampler/torch_datasets/utils/__init__.py
ocf_data_sampler/torch_datasets/utils/add_alterate_coordinate_projections.py
ocf_data_sampler/torch_datasets/utils/config_normalization_values_to_dicts.py
ocf_data_sampler-1.0.9.dist-info/METADATA
ocf_data_sampler-1.0.9.dist-info/WHEEL
ocf_data_sampler-1.0.9.dist-info/top_level.txt
ocf_data_sampler-1.0.9.dist-info/RECORD
