Metadata-Version: 2.4
Name: ocf-data-sampler
Version: 1.0.9
Author: James Fulton, Peter Dudfield
Author-email: Open Climate Fix team <info@openclimatefix.org>
License: MIT License
Project-URL: repository, https://github.com/openclimatefix/ocf-data-sampler
Classifier: Programming Language :: Python :: 3
Classifier: License :: OSI Approved :: MIT License
Requires-Python: <3.14,>=3.11
Requires-Dist: torch
Requires-Dist: numpy
Requires-Dist: pandas
Requires-Dist: xarray
Requires-Dist: zarr
Requires-Dist: numcodecs
Requires-Dist: dask
Requires-Dist: matplotlib
Requires-Dist: pvlib
Requires-Dist: pydantic>=2.11.8
Requires-Dist: pyproj
Requires-Dist: pyaml_env
Requires-Dist: pyresample
Requires-Dist: h5netcdf
Requires-Dist: xarray-tensorstore==0.1.5
Requires-Dist: zarr>=3
